[
    {
        "id": "38122733-fd8b-412b-ad6e-2233209ba5cb",
        "type": "reel",
        "likes": 570,
        "comments": 68,
        "shares": 6
    },
    {
        "id": "76bc852d-d294-48fa-9663-1131ea8907b2",
        "type": "reel",
        "likes": 118,
        "comments": 248,
        "shares": 17
    },
    {
        "id": "90141125-afc0-4898-ab1b-4e80a253f2d4",
        "type": "reel",
        "likes": 983,
        "comments": 193,
        "shares": 68
    },
    {
        "id": "c34a91aa-51db-413c-a30f-861539ab1df7",
        "type": "reel",
        "likes": 84,
        "comments": 24,
        "shares": 71
    },
    {
        "id": "363fc966-a58b-4e03-af8f-86f8da0bb1cb",
        "type": "reel",
        "likes": 29,
        "comments": 283,
        "shares": 77
    },
    {
        "id": "5208a85a-3120-4220-bf38-e2a681cafbcc",
        "type": "reel",
        "likes": 782,
        "comments": 215,
        "shares": 75
    },
    {
        "id": "82edd7f8-cc41-4ac7-8ecc-f5882b11a210",
        "type": "carousel",
        "likes": 136,
        "comments": 44,
        "shares": 95
    },
    {
        "id": "e780f450-604d-4f52-b03d-90979edf8614",
        "type": "carousel",
        "likes": 34,
        "comments": 299,
        "shares": 89
    },
    {
        "id": "e6c5d65d-1f8a-4dfd-a1f4-c41222b0281f",
        "type": "static",
        "likes": 879,
        "comments": 141,
        "shares": 21
    },
    {
        "id": "7a1ab224-4b02-4515-965a-3d3e7d89e2ea",
        "type": "carousel",
        "likes": 419,
        "comments": 200,
        "shares": 84
    },
    {
        "id": "1b69e603-42b3-455c-98c4-b080bf05f8d6",
        "type": "static",
        "likes": 822,
        "comments": 162,
        "shares": 93
    },
    {
        "id": "3a24377c-6043-4e5d-a66e-810a69e91f6b",
        "type": "reel",
        "likes": 905,
        "comments": 18,
        "shares": 95
    },
    {
        "id": "9ac6f515-ca74-466d-bae8-fada29693fd4",
        "type": "reel",
        "likes": 693,
        "comments": 117,
        "shares": 96
    },
    {
        "id": "6731b620-d312-4bf1-a62e-0f1035f94039",
        "type": "carousel",
        "likes": 345,
        "comments": 76,
        "shares": 30
    },
    {
        "id": "b6a0f4d8-91c2-44bf-8869-7de1699ec3c4",
        "type": "carousel",
        "likes": 250,
        "comments": 218,
        "shares": 23
    },
    {
        "id": "f82c39b7-f164-45e1-bde4-970bc96edee0",
        "type": "static",
        "likes": 748,
        "comments": 285,
        "shares": 97
    },
    {
        "id": "117f868c-1318-4f7a-813a-da00e040dba0",
        "type": "static",
        "likes": 499,
        "comments": 51,
        "shares": 51
    },
    {
        "id": "4c3a3851-0a30-44f7-9a42-be528cccd94e",
        "type": "reel",
        "likes": 999,
        "comments": 180,
        "shares": 97
    },
    {
        "id": "08953b77-8149-4add-a2ff-374940bc8318",
        "type": "reel",
        "likes": 25,
        "comments": 270,
        "shares": 79
    },
    {
        "id": "4575bb9a-1fc7-4aa4-b31a-2c76996f03b6",
        "type": "carousel",
        "likes": 319,
        "comments": 278,
        "shares": 20
    },
    {
        "id": "415985ba-9265-43bc-879a-39e29a974ea7",
        "type": "carousel",
        "likes": 110,
        "comments": 145,
        "shares": 22
    },
    {
        "id": "758f6777-e6bc-47b5-afb3-16905b9584f8",
        "type": "carousel",
        "likes": 646,
        "comments": 245,
        "shares": 58
    },
    {
        "id": "5d443634-44c7-444b-b6de-a63aa8d09366",
        "type": "carousel",
        "likes": 835,
        "comments": 102,
        "shares": 16
    },
    {
        "id": "55c51e50-e15e-4e56-ab12-3c76be414c86",
        "type": "carousel",
        "likes": 579,
        "comments": 90,
        "shares": 95
    },
    {
        "id": "a61966c8-7348-4dc7-aa52-5311d304ed81",
        "type": "static",
        "likes": 206,
        "comments": 234,
        "shares": 47
    },
    {
        "id": "3328d9d1-4daa-45c0-952b-541b933b1ba2",
        "type": "reel",
        "likes": 174,
        "comments": 120,
        "shares": 76
    },
    {
        "id": "17bc6648-2da9-4efb-8baf-47e9a0ddde86",
        "type": "static",
        "likes": 543,
        "comments": 161,
        "shares": 63
    },
    {
        "id": "1e46a28f-4115-41e7-a2c8-b02293276097",
        "type": "carousel",
        "likes": 937,
        "comments": 214,
        "shares": 27
    },
    {
        "id": "6c143bdc-661a-4613-aa0c-bf2fa19ca2d9",
        "type": "carousel",
        "likes": 549,
        "comments": 6,
        "shares": 94
    },
    {
        "id": "492fcd35-d500-4c8a-8f61-40274b514098",
        "type": "carousel",
        "likes": 265,
        "comments": 289,
        "shares": 80
    },
    {
        "id": "e173052a-339b-45ef-9014-0f7823a9523b",
        "type": "static",
        "likes": 829,
        "comments": 157,
        "shares": 2
    },
    {
        "id": "55a142dd-183c-485f-808a-f8d6f1d6c211",
        "type": "reel",
        "likes": 836,
        "comments": 205,
        "shares": 66
    },
    {
        "id": "a0fa0f45-f1bf-4598-9c08-869a54014715",
        "type": "reel",
        "likes": 268,
        "comments": 86,
        "shares": 33
    },
    {
        "id": "e65c2a67-3ace-4876-9d41-9270c2084dea",
        "type": "carousel",
        "likes": 335,
        "comments": 135,
        "shares": 19
    },
    {
        "id": "00ee9b29-b467-46ee-b490-97c827ca5b64",
        "type": "static",
        "likes": 185,
        "comments": 197,
        "shares": 10
    },
    {
        "id": "d8b87d9d-86cd-4dd0-b1da-15cd187f99d8",
        "type": "reel",
        "likes": 949,
        "comments": 210,
        "shares": 96
    },
    {
        "id": "3b58e6e8-ea8b-4825-bb16-7d190d7900ca",
        "type": "static",
        "likes": 461,
        "comments": 172,
        "shares": 50
    },
    {
        "id": "371754ab-9bd0-4c42-966b-d351f6dfc7ad",
        "type": "carousel",
        "likes": 633,
        "comments": 86,
        "shares": 4
    },
    {
        "id": "5dde7b1c-ffb1-4e1c-bf06-e41350f718d6",
        "type": "carousel",
        "likes": 555,
        "comments": 83,
        "shares": 28
    },
    {
        "id": "ae164c83-e6a0-4660-9c39-45a54e390290",
        "type": "static",
        "likes": 986,
        "comments": 15,
        "shares": 4
    },
    {
        "id": "f59cd391-63b0-4b5c-aeba-163cf9177b79",
        "type": "static",
        "likes": 996,
        "comments": 239,
        "shares": 43
    },
    {
        "id": "c6e37267-e93f-47bc-8738-e7e4bd707b7d",
        "type": "reel",
        "likes": 90,
        "comments": 37,
        "shares": 99
    },
    {
        "id": "5fbe262b-c73a-400a-8770-8456bb961961",
        "type": "static",
        "likes": 598,
        "comments": 249,
        "shares": 98
    },
    {
        "id": "98d3910d-e67d-4fe8-b79f-7e3d15abc532",
        "type": "static",
        "likes": 441,
        "comments": 38,
        "shares": 68
    },
    {
        "id": "db508b31-ff6a-4056-a0a6-112c0e66110a",
        "type": "reel",
        "likes": 719,
        "comments": 77,
        "shares": 54
    },
    {
        "id": "8e53ecb9-346b-4af0-864d-8f8ac85361c8",
        "type": "carousel",
        "likes": 891,
        "comments": 235,
        "shares": 44
    },
    {
        "id": "dac55255-aacd-47de-bc6f-d062a94b4eab",
        "type": "reel",
        "likes": 761,
        "comments": 195,
        "shares": 81
    },
    {
        "id": "85230908-4cea-4ee3-bcee-d20d6d1eb116",
        "type": "carousel",
        "likes": 611,
        "comments": 167,
        "shares": 27
    },
    {
        "id": "d3b366ea-305a-4121-b110-bad28f0d9afa",
        "type": "reel",
        "likes": 771,
        "comments": 159,
        "shares": 21
    },
    {
        "id": "ff5c7eb8-0539-49bf-b54a-bfdfd7b5feea",
        "type": "carousel",
        "likes": 520,
        "comments": 153,
        "shares": 7
    },
    {
        "id": "83978625-618f-4b44-92f6-17580d230c57",
        "type": "reel",
        "likes": 746,
        "comments": 87,
        "shares": 81
    },
    {
        "id": "2ea38cbe-bba7-4865-8cd5-3980e42ecf6b",
        "type": "static",
        "likes": 980,
        "comments": 200,
        "shares": 16
    },
    {
        "id": "869807e6-e880-4ee8-8f64-023b09df3787",
        "type": "carousel",
        "likes": 854,
        "comments": 186,
        "shares": 10
    },
    {
        "id": "a100bb50-290b-4cb2-8b55-1239ac5ec733",
        "type": "reel",
        "likes": 102,
        "comments": 26,
        "shares": 95
    },
    {
        "id": "1d0727a4-f7f9-42ff-84d2-66c7ba923f7f",
        "type": "static",
        "likes": 115,
        "comments": 212,
        "shares": 25
    },
    {
        "id": "8afb867e-da9e-468f-873f-8fda7e411822",
        "type": "static",
        "likes": 62,
        "comments": 165,
        "shares": 18
    },
    {
        "id": "e2860b42-2a49-4f80-999f-93aa2a858fb7",
        "type": "static",
        "likes": 907,
        "comments": 122,
        "shares": 39
    },
    {
        "id": "f77c0cc2-1434-470d-ba42-e28ffd56f06f",
        "type": "carousel",
        "likes": 716,
        "comments": 29,
        "shares": 19
    },
    {
        "id": "c82f598a-f900-4617-ae74-dda4944b10d4",
        "type": "static",
        "likes": 305,
        "comments": 41,
        "shares": 66
    },
    {
        "id": "51b9ab70-46e7-436f-b6aa-34fa915f6e82",
        "type": "carousel",
        "likes": 597,
        "comments": 243,
        "shares": 79
    },
    {
        "id": "efe85ff8-071f-43b3-be08-53e48e924ae1",
        "type": "static",
        "likes": 414,
        "comments": 3,
        "shares": 37
    },
    {
        "id": "6d80c1fd-c01a-4ddf-a547-5ff2dc799bc0",
        "type": "carousel",
        "likes": 45,
        "comments": 285,
        "shares": 95
    },
    {
        "id": "0686bf9f-64f2-4501-a260-7c55730f6b7e",
        "type": "static",
        "likes": 592,
        "comments": 74,
        "shares": 16
    },
    {
        "id": "8b975be9-a86c-4b03-854e-358b6d7ffaaa",
        "type": "reel",
        "likes": 246,
        "comments": 121,
        "shares": 82
    },
    {
        "id": "69be7e09-a64b-41ca-8af7-43b5e00066a4",
        "type": "carousel",
        "likes": 452,
        "comments": 117,
        "shares": 17
    },
    {
        "id": "6d2e295f-e7a0-460e-9392-eb2f779527de",
        "type": "carousel",
        "likes": 495,
        "comments": 291,
        "shares": 55
    },
    {
        "id": "f3687202-43ec-40bd-a1be-d8593b6b4b48",
        "type": "static",
        "likes": 522,
        "comments": 10,
        "shares": 80
    },
    {
        "id": "d785bc04-4ceb-45d0-a592-629207bd1143",
        "type": "reel",
        "likes": 789,
        "comments": 94,
        "shares": 99
    },
    {
        "id": "38d28be2-6b6f-4098-842d-eab07e177623",
        "type": "carousel",
        "likes": 510,
        "comments": 9,
        "shares": 32
    },
    {
        "id": "5e5c64ac-6baa-4318-90a0-923babfd80d7",
        "type": "carousel",
        "likes": 506,
        "comments": 280,
        "shares": 10
    },
    {
        "id": "ecf3ad63-be5c-4733-994f-eda244b9ecb2",
        "type": "carousel",
        "likes": 591,
        "comments": 130,
        "shares": 37
    },
    {
        "id": "cb7dc93b-2d37-4892-8703-edbe3ab620d6",
        "type": "static",
        "likes": 864,
        "comments": 239,
        "shares": 63
    },
    {
        "id": "0f1f6a6d-3354-4ede-a967-a2c704f4a602",
        "type": "reel",
        "likes": 165,
        "comments": 195,
        "shares": 41
    },
    {
        "id": "8dfb8d06-3a15-457e-b7a3-cbfd38fa5d9b",
        "type": "carousel",
        "likes": 232,
        "comments": 250,
        "shares": 74
    },
    {
        "id": "dbb56e29-77e4-410f-a439-47fd0e180758",
        "type": "reel",
        "likes": 490,
        "comments": 233,
        "shares": 91
    },
    {
        "id": "693f079c-0e05-4f62-a881-6eca58b22d96",
        "type": "carousel",
        "likes": 185,
        "comments": 156,
        "shares": 80
    },
    {
        "id": "7eed3472-d99c-46a4-9a93-41baa5108cc5",
        "type": "reel",
        "likes": 864,
        "comments": 259,
        "shares": 5
    },
    {
        "id": "c8bde706-9578-499e-9f6e-5601c415ee2a",
        "type": "reel",
        "likes": 819,
        "comments": 215,
        "shares": 75
    },
    {
        "id": "60b14fd3-38e4-4b32-a0a4-130c3ae4fe36",
        "type": "carousel",
        "likes": 987,
        "comments": 147,
        "shares": 95
    },
    {
        "id": "bc291c86-6469-49ef-8f29-06dcc74d1b70",
        "type": "reel",
        "likes": 171,
        "comments": 111,
        "shares": 70
    },
    {
        "id": "f07eb40d-6357-4e19-bbd3-9a5d9ca80012",
        "type": "carousel",
        "likes": 931,
        "comments": 129,
        "shares": 75
    },
    {
        "id": "9bc15b1e-5030-4973-aac1-4227b8e23365",
        "type": "static",
        "likes": 413,
        "comments": 112,
        "shares": 36
    },
    {
        "id": "49e5cb7c-4ab6-4282-a740-7c0d6d637788",
        "type": "reel",
        "likes": 281,
        "comments": 235,
        "shares": 50
    },
    {
        "id": "2e9a8ded-b3d9-4ab4-8f67-d37e5a1a5626",
        "type": "static",
        "likes": 804,
        "comments": 61,
        "shares": 53
    },
    {
        "id": "c9511e15-c39d-4de8-a60d-19087a56954d",
        "type": "static",
        "likes": 462,
        "comments": 198,
        "shares": 48
    },
    {
        "id": "c2d633b6-00c9-42ac-a4d1-2e4f01d1e1fa",
        "type": "carousel",
        "likes": 939,
        "comments": 256,
        "shares": 77
    },
    {
        "id": "5e571daa-ec94-4615-9cd2-8bc2341ee1f2",
        "type": "reel",
        "likes": 368,
        "comments": 230,
        "shares": 37
    },
    {
        "id": "94b525d0-5ccb-41cb-803e-3b0c78d7aa0a",
        "type": "static",
        "likes": 832,
        "comments": 94,
        "shares": 97
    },
    {
        "id": "07152add-3229-4626-8ca8-4a1777c3a2f0",
        "type": "static",
        "likes": 884,
        "comments": 76,
        "shares": 12
    },
    {
        "id": "549d6740-ee26-49f0-b3f4-c6a383a148ff",
        "type": "static",
        "likes": 111,
        "comments": 119,
        "shares": 97
    },
    {
        "id": "c960776e-808a-46c5-a353-439bf365c2eb",
        "type": "carousel",
        "likes": 704,
        "comments": 8,
        "shares": 75
    },
    {
        "id": "716d9512-d815-44f2-b9ce-ece8e255a713",
        "type": "reel",
        "likes": 977,
        "comments": 190,
        "shares": 84
    },
    {
        "id": "cd48f4a5-3b2d-4976-813e-dd80eeede4d9",
        "type": "reel",
        "likes": 632,
        "comments": 120,
        "shares": 76
    },
    {
        "id": "d2a17ee2-e32c-409d-84af-be23de53d2f6",
        "type": "reel",
        "likes": 136,
        "comments": 117,
        "shares": 82
    },
    {
        "id": "3cda039e-5b47-42e2-a07b-cb069bafd677",
        "type": "reel",
        "likes": 963,
        "comments": 249,
        "shares": 28
    },
    {
        "id": "79f36c0a-b33a-42ed-9007-f7b8b85dc21f",
        "type": "carousel",
        "likes": 849,
        "comments": 201,
        "shares": 57
    },
    {
        "id": "f2c4ed3d-3e8a-494c-99b8-e758bc8bc9ce",
        "type": "static",
        "likes": 830,
        "comments": 156,
        "shares": 69
    },
    {
        "id": "a16f7e98-716f-41e0-b1bc-93cfe056e115",
        "type": "static",
        "likes": 874,
        "comments": 17,
        "shares": 69
    },
    {
        "id": "fd8665ef-9ac6-41e8-ba84-9da8450e7268",
        "type": "carousel",
        "likes": 675,
        "comments": 107,
        "shares": 89
    },
    {
        "id": "e7e3296b-5177-4759-97fa-607299d6f741",
        "type": "reel",
        "likes": 823,
        "comments": 145,
        "shares": 39
    }
]